Metadata-Version: 1.1
Name: bittrex-autotrader
Version: 0.1.0
Summary: Bittrex currency exchange autotrading script in a nutshell.
Home-page: https://github.com/nuxy/bittrex_autotrader
Author: Marc S. Brooks
Author-email: devel@mbrooks.info
License: UNKNOWN
Download-URL: https://github.com/nuxy/bittrex_autotrader/archive/0.0.0.1.0.tar.gz
Keywords: trading-bot,api-client,cryptocurrency,bittrex
Platform: UNKNOWN
